lucasmcgregor/knightstour/Knightstour.py
lucasmcgregor/knightstour/TourReporter.py
lucasmcgregor/knightstour/__init__.py
lucasmcgregor.knightstour-0.1.4.dist-info/entry_points.txt
lucasmcgregor.knightstour-0.1.4.dist-info/LICENSE
lucasmcgregor.knightstour-0.1.4.dist-info/WHEEL
lucasmcgregor.knightstour-0.1.4.dist-info/METADATA
lucasmcgregor.knightstour-0.1.4.dist-info/RECORD
