Metadata-Version: 2.1
Name: lucasmcgregor.knightstour
Version: 0.1.4
Summary: A simplistic implementation of the knights tour
License: MIT
Author: Lucas McGregor
Author-email: lucasmcgregor@gmail.com
Requires-Python: >=3.7,<4.0
Classifier: License :: OSI Approved :: MIT License
Classifier: Programming Language :: Python :: 3
Classifier: Programming Language :: Python :: 3.7
Classifier: Programming Language :: Python :: 3.8
Classifier: Programming Language :: Python :: 3.9
